LICENSE
README.md
setup.py
multicube_braille_display/__init__.py
multicube_braille_display/language.py
multicube_braille_display.egg-info/PKG-INFO
multicube_braille_display.egg-info/SOURCES.txt
multicube_braille_display.egg-info/dependency_links.txt
multicube_braille_display.egg-info/top_level.txt