Metadata-Version: 2.1
Name: multicube-braille-display
Version: 0.0.1
Summary: It,s  Description
Author: Meliq
License-File: LICENSE
